uba_calqlator/__init__.py
uba_calqlator/calqlator.py
uba_calqlator/scope.py
uba_calqlator/timeseries.py
uba_calqlator/utils.py
uba_calqlator-1.2.2.dist-info/LICENSE
uba_calqlator-1.2.2.dist-info/METADATA
uba_calqlator-1.2.2.dist-info/WHEEL
uba_calqlator-1.2.2.dist-info/top_level.txt
uba_calqlator-1.2.2.dist-info/RECORD
