Metadata-Version: 2.1
Name: uba-calqlator
Version: 1.2.2
Summary: Functions to interact with the Seven2one TechStack via CalQlator
Home-page: http://www.seven2one.de
Author: Seven2one Informationssysteme GmbH
Author-email: info@seven2one.de
License: MIT
Classifier: Development Status :: 3 - Alpha
Classifier: Natural Language :: English
Classifier: Operating System :: OS Independent
Requires-Python: >=3.7
License-File: LICENSE
Requires-Dist: pandas
Requires-Dist: seven2one (>=2.34)
